ccparo/__init__.py
ccparo/main.py
ccparo/paro.py
ccparo-0.2.dist-info/METADATA
ccparo-0.2.dist-info/WHEEL
ccparo-0.2.dist-info/entry_points.txt
ccparo-0.2.dist-info/top_level.txt
ccparo-0.2.dist-info/RECORD
