Metadata-Version: 2.1
Name: ccparo
Version: 0.2
Requires-Dist: requests
Requires-Dist: pyperclip
